MANIFEST.in
README.md
setup.cfg
setup.py
cytopast/__init__.py
cytopast/colour_generator.py
cytopast/cytoscape_manager.py
cytopast/generate_geomap.py
cytopast/pastml_analyser.py
cytopast.egg-info/PKG-INFO
cytopast.egg-info/SOURCES.txt
cytopast.egg-info/dependency_links.txt
cytopast.egg-info/entry_points.txt
cytopast.egg-info/requires.txt
cytopast.egg-info/top_level.txt
cytopast/templates/geo_map.html
cytopast/templates/index.html
cytopast/templates/pie_tree.js
cytopast/templates/time_slider.html