Metadata-Version: 1.1
Name: cytopast
Version: 1.1.1
Summary: Visualisation of PastML trees.
Home-page: https://github.com/evolbioinfo/cytopast
Author: Anna Zhukova
Author-email: anna.zhukova@pasteur.fr
License: UNKNOWN
Keywords: PASTML,visualisation,phylogeny
Platform: UNKNOWN
Classifier: Development Status :: 5 - Production/Stable
Classifier: Environment :: Console
Classifier: Intended Audience :: Developers
Classifier: Topic :: Scientific/Engineering :: Bio-Informatics
Classifier: Topic :: Software Development
Classifier: Topic :: Software Development :: Libraries :: Python Modules
